lks_idprovider_entraid/__init__.py
lks_idprovider_entraid/config.py
lks_idprovider_entraid/provider.py
lks_idprovider_entraid/rest/__init__.py
lks_idprovider_entraid/rest/entraid_client.py
lks_idprovider_entraid/utils.py
lks_idprovider_entraid-0.1.3.dist-info/METADATA
lks_idprovider_entraid-0.1.3.dist-info/WHEEL
lks_idprovider_entraid-0.1.3.dist-info/RECORD
