Metadata-Version: 2.3
Name: lks-idprovider-entraid
Version: 0.1.3
Summary: Azure Entra ID provider implementation for LKS Identity Provider library
Author: Raul Medeiros
Author-email: rmedeiros@lksnext.com
Requires-Python: >=3.11
Classifier: Programming Language :: Python :: 3
Classifier: Programming Language :: Python :: 3.11
Classifier: Programming Language :: Python :: 3.12
Classifier: Programming Language :: Python :: 3.13
Requires-Dist: aiohttp (>=3.9.0,<4.0.0)
Requires-Dist: azure-identity (>=1.15.0,<2.0.0)
Requires-Dist: cryptography (>=45.0.6,<46.0.0)
Requires-Dist: httpx (>=0.28.1,<0.29.0)
Requires-Dist: lks-idprovider-api (>=0.1.3,<0.2.0)
Requires-Dist: pyjwt[crypto] (>=2.8.0,<3.0.0)
Requires-Dist: python-multipart (>=0.0.9,<0.1.0)
